grappelli_nested/__init__.py
grappelli_nested/admin.py
grappelli_nested/forms.py
grappelli_nested/helpers.py
grappelli_nested/models.py
grappelli_nested/views.py
grappelli_nested/static/grappelli_nested/.DS_Store
grappelli_nested/static/grappelli_nested/css/grp_nested_inline.css
grappelli_nested/static/grappelli_nested/js/grp_nested_inline.js
grappelli_nested/templates/admin/edit_inline/stacked.html
grappelli_nested/templates/admin/edit_inline/tabular.html
grappelli_nested_inlines-0.6.1.dist-info/DESCRIPTION.rst
grappelli_nested_inlines-0.6.1.dist-info/METADATA
grappelli_nested_inlines-0.6.1.dist-info/RECORD
grappelli_nested_inlines-0.6.1.dist-info/WHEEL
grappelli_nested_inlines-0.6.1.dist-info/metadata.json
grappelli_nested_inlines-0.6.1.dist-info/top_level.txt
