Metadata-Version: 2.0
Name: grappelli-nested-inlines
Version: 0.6.1
Summary: Enables nested inlines in the Django/Grappelli admin
Home-page: https://github.com/allanjamesvestal/grappelli-nested-inlines/
Author: Allan James Vestal (based on code by Alain Trinh)
Author-email: allanjamesvestal@gmail.com
License: MIT License
Download-URL: https://github.com/allanjamesvestal/grappelli-nested-inlines/archive/0.6.1.tar.gz
Platform: UNKNOWN
Classifier: Development Status :: 4 - Beta
Classifier: Environment :: Web Environment
Classifier: Framework :: Django
Classifier: Intended Audience :: Developers
Classifier: License :: OSI Approved :: MIT License
Classifier: Operating System :: OS Independent
Classifier: Programming Language :: Python
Classifier: Topic :: Software Development :: Libraries :: Python Modules
